flatnav/__init__.py
flatnav/_core.cpython-312-darwin.so
flatnav-0.1.2.dist-info/METADATA
flatnav-0.1.2.dist-info/WHEEL
flatnav-0.1.2.dist-info/top_level.txt
flatnav-0.1.2.dist-info/RECORD
