Metadata-Version: 2.1
Name: flatnav
Version: 0.1.2
Summary: A performant graph-based kNN search library with re-ordering.
Home-page: https://flatnav.net
Author: Benjamin Coleman, Blaise Munyampirwa, Vihan Lakshman
Author-email: benjamin.ray.coleman@gmail.com, blaisemunyampirwa@gmail.com, vihan@mit.edu
Maintainer-email: blaisemunyampirwa@gmail.com
License: Apache License, Version 2.0
Project-URL: Source Code, https://github.com/BlaiseMuhirwa/flatnav
Project-URL: Documentation, https://blaisemuhirwa.github.io/flatnav
Project-URL: Bug Tracker, https://github.com/BlaiseMuhirwa/flatnav/issues
Keywords: similarity search,vector databases,machine learning
Classifier: Development Status :: 4 - Beta
Classifier: Environment :: Console
Classifier: Operating System :: POSIX :: Linux
Classifier: Intended Audience :: Science/Research
Classifier: Intended Audience :: Developers
Classifier: Intended Audience :: Other Audience
Classifier: License :: OSI Approved :: Apache Software License
Classifier: Programming Language :: C++
Classifier: Programming Language :: Python :: 3
Classifier: Programming Language :: Python :: 3.8
Classifier: Programming Language :: Python :: 3.9
Classifier: Programming Language :: Python :: 3.10
Classifier: Programming Language :: Python :: 3.11
Classifier: Programming Language :: Python :: 3.12
Classifier: Topic :: System
Classifier: Topic :: Scientific/Engineering
Classifier: Topic :: Software Development
Requires-Dist: numpy<2,>=1.21.0
Requires-Dist: h5py==3.11.0
